odoo/addons/event_sale_registration_multi_qty/README.rst
odoo/addons/event_sale_registration_multi_qty/__init__.py
odoo/addons/event_sale_registration_multi_qty/__manifest__.py
odoo/addons/event_sale_registration_multi_qty/i18n/es.po
odoo/addons/event_sale_registration_multi_qty/i18n/event_sale_registration_multi_qty.pot
odoo/addons/event_sale_registration_multi_qty/i18n/it.po
odoo/addons/event_sale_registration_multi_qty/models/__init__.py
odoo/addons/event_sale_registration_multi_qty/models/event_registration.py
odoo/addons/event_sale_registration_multi_qty/models/sale_order.py
odoo/addons/event_sale_registration_multi_qty/readme/CONTRIBUTORS.rst
odoo/addons/event_sale_registration_multi_qty/readme/DESCRIPTION.rst
odoo/addons/event_sale_registration_multi_qty/readme/USAGE.rst
odoo/addons/event_sale_registration_multi_qty/static/description/icon.png
odoo/addons/event_sale_registration_multi_qty/static/description/index.html
odoo/addons/event_sale_registration_multi_qty/tests/__init__.py
odoo/addons/event_sale_registration_multi_qty/tests/test_event_sale_registration_multi_qty.py
odoo/addons/event_sale_registration_multi_qty/wizards/__init__.py
odoo/addons/event_sale_registration_multi_qty/wizards/event_edit_registration.py
odoo/addons/event_sale_registration_multi_qty/wizards/event_edit_registration.xml
odoo14_addon_event_sale_registration_multi_qty-14.0.1.0.1.dev8.dist-info/METADATA
odoo14_addon_event_sale_registration_multi_qty-14.0.1.0.1.dev8.dist-info/WHEEL
odoo14_addon_event_sale_registration_multi_qty-14.0.1.0.1.dev8.dist-info/top_level.txt
odoo14_addon_event_sale_registration_multi_qty-14.0.1.0.1.dev8.dist-info/RECORD
